courts_api/__init__.py
courts_api/api.py
courts_api/cli.py
courts_api/utils.py
courts_api/scales/__init__.py
courts_api/scales/code/__init__.py
courts_api/scales/code/downloader/__init__.py
courts_api/scales/code/downloader/forms.py
courts_api/scales/code/downloader/scraper_tools.py
courts_api/scales/code/downloader/scrapers.py
courts_api/scales/code/downloader/tools.py
courts_api/scales/code/support/__init__.py
courts_api/scales/code/support/bundler.py
courts_api/scales/code/support/core.py
courts_api/scales/code/support/counsel_functions.py
courts_api/scales/code/support/court_functions.py
courts_api/scales/code/support/data_tools.py
courts_api/scales/code/support/docket_entry_identification.py
courts_api/scales/code/support/docket_functions.py
courts_api/scales/code/support/fhandle_tools.py
courts_api/scales/code/support/fjc.py
courts_api/scales/code/support/judge_functions.py
courts_api/scales/code/support/language_tools.py
courts_api/scales/code/support/lexicon.py
courts_api/scales/code/support/mongo_connector.py
courts_api/scales/code/support/research_tools.py
courts_api/scales/code/support/scales_shell.py
courts_api/scales/code/support/settings.py
courts_api/scales/code/support/stats.py
courts_api/scales/code/support/text_functions.py
courts_api/scales/code/support/viz_tools.py
courts_api/scales/code/support/core_data/__init__.py
courts_api/scales/code/support/core_data/brmag_judges.csv
courts_api/scales/code/support/core_data/brmag_positions.csv
courts_api/scales/code/support/core_data/district_courts.csv
courts_api/scales/code/support/core_data/district_courts_94.csv
courts_api/scales/code/support/core_data/judge_demographics.csv
courts_api/scales/code/support/core_data/nature_suit.csv
courts_api/scales/code/support/core_data/statey2code.json
courts_api/scales/code/tasks/__init__.py
courts_api/scales/code/tasks/build_unique_table.py
courts_api-0.1.4.data/data/courts_api/__init__.py
courts_api-0.1.4.data/data/courts_api/brmag_judges.csv
courts_api-0.1.4.dist-info/METADATA
courts_api-0.1.4.dist-info/WHEEL
courts_api-0.1.4.dist-info/entry_points.txt
courts_api-0.1.4.dist-info/top_level.txt
courts_api-0.1.4.dist-info/RECORD
