Metadata-Version: 2.1
Name: courts-api
Version: 0.1.4
Requires-Dist: async-generator
Requires-Dist: attrs
Requires-Dist: beautifulsoup4
Requires-Dist: bs4
Requires-Dist: cchardet
Requires-Dist: cffi
Requires-Dist: chardet
Requires-Dist: charset-normalizer
Requires-Dist: click
Requires-Dist: configuration-maker
Requires-Dist: cryptography
Requires-Dist: cssselect
Requires-Dist: feedparser
Requires-Dist: filelock
Requires-Dist: future
Requires-Dist: geonamescache
Requires-Dist: h11
Requires-Dist: html5lib
Requires-Dist: idna
Requires-Dist: lxml
Requires-Dist: numpy
Requires-Dist: outcome
Requires-Dist: pandas
Requires-Dist: pathlib
Requires-Dist: probableparsing
Requires-Dist: pycparser
Requires-Dist: pyOpenSSL
Requires-Dist: PySocks
Requires-Dist: python-crfsuite
Requires-Dist: python-dateutil
Requires-Dist: python-dotenv
Requires-Dist: pytz
Requires-Dist: requests
Requires-Dist: requests-file
Requires-Dist: scipy
Requires-Dist: selenium (==4.1.0)
Requires-Dist: selenium-requests
Requires-Dist: sgmllib3k
Requires-Dist: six
Requires-Dist: sniffio
Requires-Dist: sortedcontainers
Requires-Dist: soupsieve
Requires-Dist: tldextract
Requires-Dist: tqdm
Requires-Dist: trio
Requires-Dist: trio-websocket
Requires-Dist: urllib3
Requires-Dist: urllib3-secure-extra
Requires-Dist: usaddress
Requires-Dist: webencodings
Requires-Dist: wsproto
Requires-Dist: xmltodict
